Metadata-Version: 2.2
Name: webauthn
Version: 2.5.1
Summary: Pythonic WebAuthn
Home-page: https://github.com/duo-labs/py_webauthn
Download-URL: https://github.com/duo-labs/py_webauthn/archive/2.5.1.tar.gz
Author: Duo Labs
Author-email: labs@duo.com
License: BSD
Keywords: webauthn fido2
Classifier: Development Status :: 5 - Production/Stable
Classifier: Intended Audience :: Developers
Classifier: License :: OSI Approved :: BSD License
Classifier: Programming Language :: Python :: 3
License-File: LICENSE
Requires-Dist: asn1crypto>=1.5.1
Requires-Dist: cbor2>=5.6.5
Requires-Dist: cryptography>=43.0.3
Requires-Dist: pyOpenSSL>=24.2.1
Dynamic: author
Dynamic: author-email
Dynamic: classifier
Dynamic: description
Dynamic: description-content-type
Dynamic: download-url
Dynamic: home-page
Dynamic: keywords
Dynamic: license
Dynamic: requires-dist
Dynamic: summary
